[
  {
    "code": "603439.SH",
    "name": "三力制药",
    "scores": {
      "fundamental": 56.0,
      "technical": 47,
      "fundflow": 49,
      "sentiment": 3,
      "shortterm": 13.5
    },
    "reasons": {
      "fundamental": "[中] ROE=3.1%偏低; 4个概念; 近期25条公告; 股东户数-5.8%; 解禁冲击低+0.1",
      "technical": "[低] 量能偏强(量比4.36)+10; 换手8.4%健康+5; 多头排列+15; 回踩MA10企稳+5; 下影支撑+4; 资金正向(价>中轨+量比4.36)+5",
      "fundflow": "[低] [主力25分] 主力净流入[实时]8.2%+25; [龙虎17分] [盘中]封单5545.2%流通市值+10 [盘中]秒封/一字板+7; [融资0分] [盘中]无融资数据; [锁仓7分] 流入递增锁仓+7",
      "sentiment": "[无] 换手8.4%+1; 20日涨停+1; 竞价跳空-1.4%[震荡态×1.0]→0分; 竞价成交193万+1",
      "shortterm": "[封板] 今日未涨停(参考历史) | [连板] 断板(历史1连板); 近5日温和(均涨2.8%)+5 | [开盘] 今日无数据(最近20260528) | [板块] 无概念涨停统计 | [攻击] 近10日最大涨幅10.0%+35"
    },
    "weights": {
      "fundamental": "0.6",
      "technical": "1.9",
      "fundflow": "2.0",
      "sentiment": "1.1",
      "shortterm": "1.0"
    },
    "total": 49.08888888888889,
    "resonance": {
      "count": 0,
      "threshold": 75,
      "is_resonance": false
    },
    "top3_score": 49.1,
    "pct_chg": 0
  },
  {
    "code": "002436.SZ",
    "name": "兴森科技",
    "scores": {
      "fundamental": 68.0,
      "technical": 54,
      "fundflow": 34,
      "sentiment": 0,
      "shortterm": 13.5
    },
    "reasons": {
      "fundamental": "[中] ROE=2.6%偏低; 扣非净利+308%; 13个概念; 近期3条公告; 解禁冲击低+0.1",
      "technical": "[低] 量能偏强(量比1.58)+10; 换手8.4%健康+5; 多头排列+15; 回踩MA10企稳+5; 下影支撑+4; 波动收敛(带宽37.2%)+5",
      "fundflow": "[无] [主力25分] 主力净流入[实时]9.9%+25; [龙虎5分] [盘中]封单1815.1%流通市值+10 [盘中]尾板141327-8 [盘中]开板1次+3; [盘口0分] 净流出0.93亿; [融资4分] [盘中]融资买入占比100.0%+2 [盘中]融资主力同向+2",
      "sentiment": "纯跟风弱势:涨幅仅0.0%<3%",
      "shortterm": "[封板] 今日未涨停(参考历史) | [连板] 断板(历史1连板); 近5日温和(均涨1.9%)+5 | [开盘] 今日无数据(最近20260528) | [板块] 无概念涨停统计 | [攻击] 近10日最大涨幅7.6%+35"
    },
    "weights": {
      "fundamental": "0.6",
      "technical": "1.9",
      "fundflow": "2.0",
      "sentiment": "1.1",
      "shortterm": "1.0"
    },
    "total": 46.977777777777774,
    "resonance": {
      "count": 0,
      "threshold": 75,
      "is_resonance": false
    },
    "top3_score": 47.0,
    "pct_chg": 0
  },
  {
    "code": "603629.SH",
    "name": "利通电子",
    "scores": {
      "fundamental": 72.0,
      "technical": 40,
      "fundflow": 9,
      "sentiment": 0,
      "shortterm": 32.8
    },
    "reasons": {
      "fundamental": "[中] ROE=16.2%; 扣非净利+860%; 营收+42%; 近期6条公告; 股东户数+64.3%",
      "technical": "[低] 换手11.0%健康+5; 多头排列+15; 回踩MA10企稳+5; 波动收敛(带宽59.2%)+5; 价>中轨+2; 分时强势(回撤0.7%)+3",
      "fundflow": "[无] [主力0分] 主力净流入[T-1]-0.00%-15; [龙虎0分] [盘中]封单2955.0%流通市值+10 [盘中]尾板94856-8 [盘中]开板4次-7; [盘口6分] 强承接换手/振幅2.4+6; [融资0分] [盘中]无融资数据; [锁仓3分] 流入加速+3",
      "sentiment": "纯跟风弱势:涨幅仅0.0%<3%",
      "shortterm": "[封板] 今日未涨停(参考历史) | [连板] 断板(历史1连板); 近月8次涨停+20; 断板反包+15; 近5日活跃(均涨4.2%)+15 | [开盘] 今日无数据(最近20260528) | [板块] 无概念数据+10 | [攻击] 涨停高开率3/5>50%+40; 近10日最大涨幅8.9%+35"
    },
    "weights": {
      "fundamental": "0.6",
      "technical": "1.9",
      "fundflow": "2.0",
      "sentiment": "1.1",
      "shortterm": "1.0"
    },
    "total": 43.42857142857143,
    "resonance": {
      "count": 0,
      "threshold": 75,
      "is_resonance": false
    },
    "top3_score": 43.4,
    "pct_chg": 0
  },
  {
    "code": "603186.SH",
    "name": "华正新材",
    "scores": {
      "fundamental": 68.0,
      "technical": 45,
      "fundflow": 30,
      "sentiment": 0,
      "shortterm": 22.2
    },
    "reasons": {
      "fundamental": "[中] ROE=17.4%; 扣非净利+103%; 近期2条公告; 股东户数+8.2%; 解禁冲击低+0.1",
      "technical": "[低] 量能偏强(量比1.08)+10; 换手10.1%健康+5; 多头排列+15; 回踩MA10企稳+5; 下影支撑+4; 假突破:3日2日上影-4",
      "fundflow": "[无] [主力5分] 主力净流入[实时]6.4%+25 散户接盘[T-1]-20; [龙虎18分] [盘中]封单959.4%流通市值+10 [盘中]早封板100338+8; [融资0分] [盘中]无融资数据; [锁仓7分] 流入递增锁仓+7",
      "sentiment": "纯跟风弱势:涨幅仅0.0%<3%",
      "shortterm": "[封板] 今日未涨停(参考历史) | [连板] 断板(历史1连板); 近月3次涨停+10; 断板反包+15; 近5日活跃(均涨3.3%)+15 | [开盘] 今日无数据(最近20260528) | [板块] 无概念涨停统计 | [攻击] 近10日最大涨幅10.0%+35"
    },
    "weights": {
      "fundamental": "0.6",
      "technical": "1.9",
      "fundflow": "2.0",
      "sentiment": "1.1",
      "shortterm": "1.0"
    },
    "total": 41.400000000000006,
    "resonance": {
      "count": 0,
      "threshold": 75,
      "is_resonance": false
    },
    "top3_score": 41.4,
    "pct_chg": 0
  },
  {
    "code": "002138.SZ",
    "name": "顺络电子",
    "scores": {
      "fundamental": 63.0,
      "technical": 45,
      "fundflow": 4,
      "sentiment": 0,
      "shortterm": 12.2
    },
    "reasons": {
      "fundamental": "[中] ROE=15.7%; 扣非净利-24%; 15个概念; 近期3条公告; 股东户数+20.3%",
      "technical": "[低] 量能偏强(量比1.24)+10; 换手7.0%健康+5; 多头排列+15; 回踩MA10企稳+5; 下影支撑+4; 假突破:3日2日上影-4",
      "fundflow": "[无] [龙虎2分] [盘中]封单2005.8%流通市值+10 [盘中]尾板143115-8; [盘口0分] 净流出0.69亿; [融资2分] [盘中]融资买入占比100.0%+2",
      "sentiment": "纯跟风弱势:涨幅仅0.0%<3%",
      "shortterm": "[封板] 无涨停记录 | [连板] 近期无涨停; 近5日活跃(均涨4.3%)+15 | [开盘] 今日无数据(最近20260528) | [板块] 无概念涨停统计 | [攻击] 近10日最大涨幅8.5%+35"
    },
    "weights": {
      "fundamental": "0.6",
      "technical": "1.9",
      "fundflow": "2.0",
      "sentiment": "1.1",
      "shortterm": "1.0"
    },
    "total": 38.714285714285715,
    "resonance": {
      "count": 0,
      "threshold": 75,
      "is_resonance": false
    },
    "top3_score": 38.7,
    "pct_chg": 0
  },
  {
    "code": "000636.SZ",
    "name": "风华高科",
    "scores": {
      "fundamental": 69.0,
      "technical": 35,
      "fundflow": 2,
      "sentiment": 18,
      "shortterm": 24.8
    },
    "reasons": {
      "fundamental": "[中] ROE=2.3%偏低; 扣非净利+33%; 17个概念; 近期6条公告; 股东户数-11.0%",
      "technical": "[低] 换手13.2%健康+5; 多头排列+15; 回踩MA10企稳+5; 价>中轨+2; 分时强势(回撤0.2%)+3; 板块共振(70%>MA20)+5",
      "fundflow": "[无] [主力0分] 主力净流入[T-1]0.00%-15; [龙虎0分] [盘中]封单3854.8%流通市值+10 [盘中]尾板93524-8 [盘中]开板4次-7; [盘口0分] 净流出13.05亿 对倒嫌疑换手13.2%-12; [融资2分] [盘中]融资买入占比100.0%+2",
      "sentiment": "[无] 换手13.2%+1; 20日涨停5次+3; 连板基因2连板+3; 竞价跳空6.5%[震荡态×1.0]→5分; 竞价关注度高(量比2.8)+3; 竞价量比3.2+1",
      "shortterm": "[封板] 今日未涨停(参考历史) | [连板] 断板(历史1连板); 近月5次涨停+20; 断板反包+15; 近5日活跃(均涨7.4%)+15 | [开盘] 今日无数据(最近20260528) | [板块] 无概念涨停统计 | [攻击] 近10日最大涨幅10.0%+35"
    },
    "weights": {
      "fundamental": "0.6",
      "technical": "1.9",
      "fundflow": "2.0",
      "sentiment": "1.1",
      "shortterm": "1.0"
    },
    "total": 37.91428571428572,
    "resonance": {
      "count": 0,
      "threshold": 75,
      "is_resonance": false
    },
    "top3_score": 37.9,
    "pct_chg": 0
  },
  {
    "code": "002039.SZ",
    "name": "黔源电力",
    "scores": {
      "fundamental": 73.5,
      "technical": 47,
      "fundflow": 17,
      "sentiment": 2,
      "shortterm": 6.5
    },
    "reasons": {
      "fundamental": "[中] ROE=14.4%; 扣非净利+72%; 近期1条公告; 股东户数-5.9%; 解禁冲击低+0.1",
      "technical": "[低] 放量启动(量比3.86>Top20%)+20; 换手4.7%健康+5; 回踩MA10企稳+5; 下影支撑+4; 资金正向(价>中轨+量比3.86)+5; 分时强势(回撤0.8%)+3",
      "fundflow": "[无] [主力0分] 主力净流入[T-1]-0.00%-15; [龙虎17分] [盘中]封单7938.7%流通市值+10 [盘中]秒封/一字板+7; [盘口0分] 净流出0.08亿; [融资0分] [盘中]融资买入占比100.0%+2 [盘中]融资主力同向+2 [盘中]融资3日连降-5",
      "sentiment": "[无] 竞价关注度较高(量比0.8)+1; 竞价成交342万+1",
      "shortterm": "[封板] 今日未涨停(参考历史) | [连板] 断板(历史1连板); 近5日温和(均涨1.4%)+5 | [开盘] 今日无数据(最近20260528) | [板块] 无概念涨停统计 | [攻击] 无数据"
    },
    "weights": {
      "fundamental": "0.6",
      "technical": "1.9",
      "fundflow": "2.0",
      "sentiment": "1.1",
      "shortterm": "1.0"
    },
    "total": 37.2,
    "resonance": {
      "count": 0,
      "threshold": 75,
      "is_resonance": false
    },
    "top3_score": 37.2,
    "pct_chg": 0
  },
  {
    "code": "600545.SH",
    "name": "卓郎智能",
    "scores": {
      "fundamental": 65.0,
      "technical": 32,
      "fundflow": 12,
      "sentiment": 11,
      "shortterm": 24.8
    },
    "reasons": {
      "fundamental": "[中] 扣非净利+75%; 6个概念; 近期2条公告; 股东户数+20.8%; 解禁冲击低+0.1",
      "technical": "[无] 换手11.3%健康+5; 多头排列+15; 回踩MA10企稳+5; 价>中轨+2; 分时强势(回撤0.8%)+3; 板块中性(36%>MA20)+2",
      "fundflow": "[无] [主力0分] 主力净流入[T-1]-0.00%-15; [龙虎0分] [盘中]T-1未涨停-15; [盘口10分] 持续净流入0.21亿+10; [融资2分] [盘中]融资买入占比100.0%+2",
      "sentiment": "[无] 换手11.3%+1; 20日涨停3次+3; 连板基因2连板+3; 竞价跳空1.3%[震荡态×1.0]→1分; 竞价关注度较高(量比0.7)+1; 竞价成交1024万+2",
      "shortterm": "[封板] 今日未涨停(参考历史) | [连板] 断板(历史1连板); 近月6次涨停+20; 断板反包+15; 近5日活跃(均涨5.6%)+15 | [开盘] 今日无数据(最近20260528) | [板块] 无概念涨停统计 | [攻击] 近10日最大涨幅10.0%+35"
    },
    "weights": {
      "fundamental": "0.6",
      "technical": "1.9",
      "fundflow": "2.0",
      "sentiment": "1.1",
      "shortterm": "1.0"
    },
    "total": 35.6,
    "resonance": {
      "count": 0,
      "threshold": 75,
      "is_resonance": false
    },
    "top3_score": 35.6,
    "pct_chg": 0
  },
  {
    "code": "603078.SH",
    "name": "江化微",
    "scores": {
      "fundamental": 60.0,
      "technical": 34,
      "fundflow": 27,
      "sentiment": 4,
      "shortterm": 12.2
    },
    "reasons": {
      "fundamental": "[中] 6个概念; 近期1条公告; 解禁冲击低+0.1",
      "technical": "[无] 量能偏强(量比5.17)+10; 换手7.4%健康+5; 回踩MA10企稳+5; 下影支撑+4; 资金正向(价>中轨+量比5.17)+5; 板块共振(75%>MA20)+5",
      "fundflow": "[无] [主力25分] 主力净流入[实时]18.0%+25; [龙虎0分] [盘中]封单4039.5%流通市值+10 [盘中]尾板93643-8 [盘中]开板6次-7; [盘口0分] 净流出0.30亿; [融资2分] [盘中]融资买入占比100.0%+2",
      "sentiment": "[无] 换手7.4%+1; 20日涨停+1; 竞价跳空1.2%[震荡态×1.0]→1分; 竞价成交463万+1",
      "shortterm": "[封板] 今日未涨停(参考历史) | [连板] 断板(历史1连板) | [开盘] 今日无数据(最近20260528) | [板块] 无概念涨停统计 | [攻击] 近10日最大涨幅10.0%+35"
    },
    "weights": {
      "fundamental": "0.6",
      "technical": "1.9",
      "fundflow": "2.0",
      "sentiment": "1.1",
      "shortterm": "1.0"
    },
    "total": 34.355555555555554,
    "resonance": {
      "count": 0,
      "threshold": 75,
      "is_resonance": false
    },
    "top3_score": 34.4,
    "pct_chg": 0
  },
  {
    "code": "601888.SH",
    "name": "中国中免",
    "scores": {
      "fundamental": 69.0,
      "technical": 0,
      "fundflow": 29,
      "sentiment": 3,
      "shortterm": 1.5
    },
    "reasons": {
      "fundamental": "[中] ROE=4.1%偏低; 扣非净利+21%; 19个概念; 近期4条公告; 股东户数-8.9%",
      "technical": "放量破位:收盘54.76<MA20=60.13,量比6.71>Top20%",
      "fundflow": "[无] [尾盘走弱]净流出2万+低于均价-5; [尾盘走弱]收跌+净流出+低于均价-5; [主力25分] 主力净流入[实时]11.7%+25; [龙虎0分] [盘中]封单7113.3%流通市值+10 [盘中]T-1未涨停-15; [盘口0分] 净流出1.85亿; [融资4分] [盘中]融资买入占比100.0%+2 [盘中]融资主力同向+2",
      "sentiment": "[无] 竞价关注度较高(量比0.9)+1; 竞价成交1851万+2",
      "shortterm": "[封板] 无涨停记录 | [连板] 近期无涨停 | [开盘] 今日无数据(最近20260528) | [板块] 无概念涨停统计 | [攻击] 无数据"
    },
    "weights": {
      "fundamental": "0.6",
      "technical": "1.9",
      "fundflow": "2.0",
      "sentiment": "1.1",
      "shortterm": "1.0"
    },
    "total": 27.756756756756758,
    "resonance": {
      "count": 0,
      "threshold": 75,
      "is_resonance": false
    },
    "top3_score": 27.8,
    "pct_chg": 0
  },
  {
    "code": "002210.SZ",
    "name": "飞马国际",
    "scores": {
      "fundamental": 0,
      "technical": 0,
      "fundflow": 34,
      "sentiment": 21,
      "shortterm": 22.2
    },
    "reasons": {
      "fundamental": "财务避雷否决: 商誉占比43%>30%",
      "technical": "放量破位:收盘2.85<MA20=2.99,量比14.35>Top20%",
      "fundflow": "[无] [主力25分] 主力净流入[实时]7.9%+25; [龙虎9分] [盘中]封单17369.9%流通市值+10 [盘中]尾板93403-8 [盘中]秒封/一字板+7; [盘口0分] 净流出0.16亿; [融资0分] [盘中]融资买入占比100.0%+2 [盘中]融资主力同向+2 [盘中]融资3日连降-5",
      "sentiment": "[无] 20日涨停2次+3; 连板基因3连板+3; 竞价跳空7.0%[震荡态×1.0]→5分; 竞价关注度极高(量比14.2)+5; 竞价量比12.4+3",
      "shortterm": "[封板] 今日未涨停(参考历史) | [连板] 断板(历史1连板); 近月5次涨停+20; 断板反包+15; 近5日温和(均涨1.1%)+5 | [开盘] 今日无数据(最近20260528) | [板块] 无概念涨停统计 | [攻击] 近10日最大涨幅10.0%+35"
    },
    "weights": {
      "fundamental": "0.6",
      "technical": "1.9",
      "fundflow": "2.0",
      "sentiment": "1.1",
      "shortterm": "1.0"
    },
    "total": 27.634146341463417,
    "resonance": {
      "count": 0,
      "threshold": 75,
      "is_resonance": false
    },
    "top3_score": 27.6,
    "pct_chg": 0
  },
  {
    "code": "002317.SZ",
    "name": "众生药业",
    "scores": {
      "fundamental": 68.0,
      "technical": 22,
      "fundflow": 13,
      "sentiment": 8,
      "shortterm": 20.0
    },
    "reasons": {
      "fundamental": "[中] 扣非净利+31%; 17个概念; 近期5条公告; 解禁冲击低+0.1",
      "technical": "[无] 换手4.0%健康+5; 多头排列+15; 下影支撑+4; 假突破:3日2日上影-4; 价>中轨+2; 板块弱势(<20%>MA20)天花板74分",
      "fundflow": "[无] [尾盘走弱]净流出1万+低于均价-5; [尾盘走弱]收跌+净流出+低于均价-5; [主力0分] 主力净流入[T-1]-0.00%-15; [龙虎9分] [盘中]封单11961.3%流通市值+10 [盘中]尾板93000-8 [盘中]秒封/一字板+7; [盘口0分] 净流出0.61亿; [融资4分] [盘中]融资买入占比100.0%+2 [盘中]融资主力同向+2",
      "sentiment": "[无] 20日涨停2次+3; 连板基因2连板+3; 竞价关注度较高(量比0.5)+1; 竞价成交358万+1",
      "shortterm": "[封板] 今日未涨停(参考历史) | [连板] 断板(历史2连板) | [开盘] 今日无数据(最近20260528); 实时换手偏大(2260.0%)+15; 实时量比119.0+10 | [板块] 无概念涨停统计 | [攻击] 涨停高开率2/2>50%+40 | [竞价] 竞价正常(量比119.0开-99.3%)+5; 竞价换手2260.00%+5"
    },
    "weights": {
      "fundamental": "0.6",
      "technical": "1.9",
      "fundflow": "2.0",
      "sentiment": "1.1",
      "shortterm": "1.0"
    },
    "total": 24.133333333333333,
    "resonance": {
      "count": 0,
      "threshold": 75,
      "is_resonance": false
    },
    "top3_score": 24.1,
    "pct_chg": 0
  },
  {
    "code": "002146.SZ",
    "name": "荣盛发展",
    "scores": {
      "fundamental": 0,
      "technical": 0,
      "fundflow": 44,
      "sentiment": 8,
      "shortterm": 1.5
    },
    "reasons": {
      "fundamental": "财务避雷否决: 负债率94%>70%且经营现金流为负",
      "technical": "放量破位:收盘1.25<MA20=1.30,量比11.17>Top20%",
      "fundflow": "[低] [主力25分] 主力净流入[实时]14.2%+25; [龙虎9分] [盘中]封单14970.0%流通市值+10 [盘中]尾板93951-8 [盘中]秒封/一字板+7; [盘口10分] 持续净流入0.15亿+10 超大单主导+4; [融资0分] [盘中]融资买入占比100.0%+2 [盘中]融资3日连降-5",
      "sentiment": "[无] 竞价跳空1.6%[震荡态×1.0]→1分; 竞价关注度极高(量比3.7)+5; 竞价量比3.9+1",
      "shortterm": "[封板] 无涨停记录 | [连板] 近期无涨停 | [开盘] 今日无数据(最近20260528) | [板块] 无概念涨停统计 | [攻击] 无数据"
    },
    "weights": {
      "fundamental": "0.6",
      "technical": "1.9",
      "fundflow": "2.0",
      "sentiment": "1.1",
      "shortterm": "1.0"
    },
    "total": 23.975609756097562,
    "resonance": {
      "count": 0,
      "threshold": 75,
      "is_resonance": false
    },
    "top3_score": 24.0,
    "pct_chg": 0
  },
  {
    "code": "605198.SH",
    "name": "安德利",
    "scores": {
      "fundamental": 52.0,
      "technical": 16,
      "fundflow": 9,
      "sentiment": 5,
      "shortterm": 21.5
    },
    "reasons": {
      "fundamental": "[低] ROE=12.2%; 扣非净利-18%; 近期6条公告; 解禁冲击低+0.1",
      "technical": "[无] 换手1.4%健康+5; 回踩MA20企稳+3; 下影支撑+4; 价>中轨+2; 板块中性(33%>MA20)+2",
      "fundflow": "[无] [主力0分] 主力净流入[T-1]-0.00%-15; [龙虎9分] [盘中]封单4842.1%流通市值+10 [盘中]尾板93839-8 [盘中]秒封/一字板+7; [盘口0分] 净流出0.00亿; [融资0分] [盘中]无融资数据",
      "sentiment": "[无] 20日涨停2次+3; 竞价跳空2.0%[震荡态×1.0]→1分; 竞价成交101万+1",
      "shortterm": "[封板] 今日未涨停(参考历史) | [连板] 断板(历史1连板); 近5日温和(均涨1.3%)+5 | [开盘] 今日无数据(最近20260528) | [板块] 无概念涨停统计 | [攻击] 涨停高开率2/2>50%+40; 近10日最大涨幅10.0%+35"
    },
    "weights": {
      "fundamental": "0.6",
      "technical": "1.9",
      "fundflow": "2.0",
      "sentiment": "1.1",
      "shortterm": "1.0"
    },
    "total": 23.74285714285714,
    "resonance": {
      "count": 0,
      "threshold": 75,
      "is_resonance": false
    },
    "top3_score": 23.7,
    "pct_chg": 0
  },
  {
    "code": "002639.SZ",
    "name": "雪人集团",
    "scores": {
      "fundamental": 0,
      "technical": 7,
      "fundflow": 43,
      "sentiment": 0,
      "shortterm": 13.5
    },
    "reasons": {
      "fundamental": "财务避雷否决: 扣非净利润连续亏损(无困境反转)",
      "technical": "[无] 换手12.1%健康+5; 空头排列-10; MA60下倾-5; 回踩MA10企稳+5; 收盘<=MA20-5; 分时走弱(价<中轨)-8",
      "fundflow": "[低] [主力0分] 主力净流入[T-1]0.00%-15; [龙虎25分] [盘中]封单14679.9%流通市值+10 [盘中]早封板101418+8 [盘中]秒封/一字板+7; [盘口4分] 超大单主导+4; [融资4分] [盘中]融资买入占比100.0%+2 [盘中]融资主力同向+2; [锁仓10分] 流入递增锁仓+7 流入加速+3",
      "sentiment": "纯跟风弱势:涨幅仅0.0%<3%",
      "shortterm": "[封板] 今日未涨停(参考历史) | [连板] 断板(历史1连板); 近5日温和(均涨1.5%)+5 | [开盘] 今日无数据(最近20260528) | [板块] 无概念涨停统计 | [攻击] 近10日最大涨幅10.0%+35"
    },
    "weights": {
      "fundamental": "0.6",
      "technical": "1.9",
      "fundflow": "2.0",
      "sentiment": "1.1",
      "shortterm": "1.0"
    },
    "total": 23.020408163265305,
    "resonance": {
      "count": 0,
      "threshold": 75,
      "is_resonance": false
    },
    "top3_score": 23.0,
    "pct_chg": 0
  },
  {
    "code": "603076.SH",
    "name": "乐惠国际",
    "scores": {
      "fundamental": 58.0,
      "technical": 7,
      "fundflow": 26,
      "sentiment": 0,
      "shortterm": 1.5
    },
    "reasons": {
      "fundamental": "[中] ROE=2.0%偏低; 扣非净利+27%; 营收+56%; 近期2条公告; 股东户数+7.0%",
      "technical": "[无] 换手5.8%健康+5; 空头排列-10; MA60下倾-5; 收盘<=MA20-5; 分时走弱(价<中轨)-8; 板块中性(20%>MA20)+2",
      "fundflow": "[无] [主力0分] 主力净流入[T-1]-0.00%-15 连续3日净流入+10; [龙虎9分] [盘中]封单17440.0%流通市值+10 [盘中]尾板94405-8 [盘中]秒封/一字板+7; [盘口10分] 持续净流入0.04亿+10; [融资4分] [盘中]融资买入占比100.0%+2 [盘中]融资主力同向+2; [锁仓3分] 无抛压+3",
      "sentiment": "纯跟风弱势:涨幅仅0.0%<3%",
      "shortterm": "[封板] 无涨停记录 | [连板] 近期无涨停 | [开盘] 今日无数据(最近20260528) | [板块] 无概念涨停统计 | [攻击] 无数据"
    },
    "weights": {
      "fundamental": "0.6",
      "technical": "1.9",
      "fundflow": "2.0",
      "sentiment": "1.1",
      "shortterm": "1.0"
    },
    "total": 22.244444444444444,
    "resonance": {
      "count": 0,
      "threshold": 75,
      "is_resonance": false
    },
    "top3_score": 22.2,
    "pct_chg": 0
  },
  {
    "code": "603716.SH",
    "name": "塞力医疗",
    "scores": {
      "fundamental": 71.0,
      "technical": 9,
      "fundflow": 20,
      "sentiment": 0,
      "shortterm": 5.2
    },
    "reasons": {
      "fundamental": "[中] 扣非净利+38%; 8个概念; 近期4条公告; 股东户数-18.5%; 解禁冲击低+0.1",
      "technical": "[无] 换手3.9%健康+5; 空头排列-10; MA60下倾-5; 收盘<=MA20-5; 下影支撑+4; 分时走弱(价<中轨)-8",
      "fundflow": "[无] [主力0分] 主力净流入[T-1]-0.00%-15; [龙虎17分] [盘中]封单29134.0%流通市值+10 [盘中]秒封/一字板+7; [融资0分] [盘中]无融资数据; [锁仓3分] 流入加速+3",
      "sentiment": "纯跟风弱势:涨幅仅0.0%<3%",
      "shortterm": "[封板] 今日未涨停(参考历史) | [连板] 断板(历史1连板) | [开盘] 今日无数据(最近20260528) | [板块] 无概念涨停统计 | [攻击] 无数据"
    },
    "weights": {
      "fundamental": "0.6",
      "technical": "1.9",
      "fundflow": "2.0",
      "sentiment": "1.1",
      "shortterm": "1.0"
    },
    "total": 22.15555555555555,
    "resonance": {
      "count": 0,
      "threshold": 75,
      "is_resonance": false
    },
    "top3_score": 22.2,
    "pct_chg": 0
  },
  {
    "code": "002981.SZ",
    "name": "朝阳科技",
    "scores": {
      "fundamental": 0,
      "technical": 36,
      "fundflow": 0,
      "sentiment": 0,
      "shortterm": 1.5
    },
    "reasons": {
      "fundamental": "财务避雷否决: 扣非净利润连续亏损(无困境反转)",
      "technical": "[低] 换手2.4%健康+5; 多头排列+15; MA60下倾-5; 回踩MA10企稳+5; 下影支撑+4; 波动收敛(带宽7.4%)+5",
      "fundflow": "[无] [主力0分] 主力净流入[T-1]0.00%-15; [龙虎0分] [盘中]T-1未涨停-15; [盘口0分] 净流出0.09亿; [融资0分] [盘中]无融资数据",
      "sentiment": "[无] 无明显信号",
      "shortterm": "[封板] 无涨停记录 | [连板] 近期无涨停 | [开盘] 今日无数据(最近20260528) | [板块] 无概念涨停统计 | [攻击] 无数据"
    },
    "weights": {
      "fundamental": "0.6",
      "technical": "1.9",
      "fundflow": "2.0",
      "sentiment": "1.1",
      "shortterm": "1.0"
    },
    "total": 19.971428571428568,
    "resonance": {
      "count": 0,
      "threshold": 75,
      "is_resonance": false
    },
    "top3_score": 20.0,
    "pct_chg": 0
  },
  {
    "code": "001328.SZ",
    "name": "登康口腔",
    "scores": {
      "fundamental": 64.0,
      "technical": 0,
      "fundflow": 5,
      "sentiment": 0,
      "shortterm": 1.5
    },
    "reasons": {
      "fundamental": "[中] ROE=12.2%; 扣非净利+32%; 近期2条公告; 解禁冲击低+0.1",
      "technical": "资金持续出逃:近2日净流出+收盘/中轨0.938<0.99",
      "fundflow": "[无] [主力0分] 主力净流入[T-1]-0.00%-15; [龙虎3分] [盘中]封单985.0%流通市值+10 [盘中]开板5次-7; [融资2分] [盘中]融资买入占比100.0%+2",
      "sentiment": "[无] 无明显信号",
      "shortterm": "[封板] 无涨停记录 | [连板] 近期无涨停 | [开盘] 今日无数据(最近20260528) | [板块] 无概念数据+10 | [攻击] 无数据"
    },
    "weights": {
      "fundamental": "0.6",
      "technical": "1.9",
      "fundflow": "2.0",
      "sentiment": "1.1",
      "shortterm": "1.0"
    },
    "total": 13.86111111111111,
    "resonance": {
      "count": 0,
      "threshold": 75,
      "is_resonance": false
    },
    "top3_score": 13.9,
    "pct_chg": 0
  },
  {
    "code": "001210.SZ",
    "name": "金房能源",
    "scores": {
      "fundamental": 51.0,
      "technical": 9,
      "fundflow": 7,
      "sentiment": 7,
      "shortterm": 12.0
    },
    "reasons": {
      "fundamental": "[低] 近期1条公告; 股东户数+20.4%; 解禁冲击低+0.1",
      "technical": "[无] 换手6.8%健康+5; 下影支撑+4; 假突破:3日3日上影-4; 价>中轨+2; 板块中性(25%>MA20)+2",
      "fundflow": "[无] [主力0分] 主力净流入[T-1]0.00%-15; [龙虎0分] [盘中]封单1798.0%流通市值+10 [盘中]尾板93830-8 [盘中]开板6次-7; [盘口4分] 超大单主导+4; [融资0分] [盘中]无融资数据; [锁仓3分] 流入加速+3",
      "sentiment": "[无] 换手6.8%+1; 20日涨停2次+3; 连板基因2连板+3",
      "shortterm": "[封板] 今日未涨停(参考历史) | [连板] 断板(历史2连板) | [开盘] 今日无数据(最近20260528); 实时换手偏大(2891.0%)+15; 实时量比112.0+10 | [板块] 无概念数据+10 | [攻击] 无数据 | [竞价] 竞价正常(量比112.0开-95.5%)+5; 竞价换手2891.00%+5"
    },
    "weights": {
      "fundamental": "0.6",
      "technical": "1.9",
      "fundflow": "2.0",
      "sentiment": "1.1",
      "shortterm": "1.0"
    },
    "total": 13.71111111111111,
    "resonance": {
      "count": 0,
      "threshold": 75,
      "is_resonance": false
    },
    "top3_score": 13.7,
    "pct_chg": 0
  },
  {
    "code": "600513.SH",
    "name": "联环药业",
    "scores": {
      "fundamental": 0,
      "technical": 0,
      "fundflow": 0,
      "sentiment": 3,
      "shortterm": 5.2
    },
    "reasons": {
      "fundamental": "财务避雷否决: 扣非净利润连续亏损(无困境反转)",
      "technical": "资金持续出逃:近2日净流出+收盘/中轨0.866<0.99",
      "fundflow": "[无] [主力0分] 主力净流入[T-1]-0.00%-15 散户接盘[T-1]-20; [龙虎0分] [盘中]封单36170.6%流通市值+10 [盘中]T-1未涨停-15; [融资0分] [盘中]无融资数据",
      "sentiment": "[无] 连板基因2连板+3",
      "shortterm": "[封板] 今日未涨停(参考历史) | [连板] 断板(历史2连板) | [开盘] 今日无数据(最近20260528) | [板块] 无概念涨停统计 | [攻击] 无数据"
    },
    "weights": {
      "fundamental": "0.6",
      "technical": "1.9",
      "fundflow": "2.0",
      "sentiment": "1.1",
      "shortterm": "1.0"
    },
    "total": 3.148148148148148,
    "resonance": {
      "count": 0,
      "threshold": 75,
      "is_resonance": false
    },
    "top3_score": 3.1,
    "pct_chg": 0
  }
]