[
  {
    "code": "000519.SZ",
    "name": "中兵红箭",
    "scores": {
      "fundamental": 76.0,
      "technical": 38,
      "fundflow": 42,
      "sentiment": 3,
      "shortterm": 1.5
    },
    "reasons": {
      "fundamental": "[高] ROE=0.4%偏低; 扣非净利+142%; 营收+181%; 13个概念; 近期7条公告",
      "technical": "[低] 放量启动(量比6.18>Top20%)+20; 换手3.7%健康+5; MA60下倾-5; 回踩MA10企稳+5; 资金正向(价>中轨+量比6.18)+5; 分时强势(回撤0.3%)+3",
      "fundflow": "[低] [主力25分] 主力净流入[实时]11.9%+25; [龙虎0分] [盘中]封单977.2%流通市值+10 [盘中]T-1未涨停-15; [盘口10分] 持续净流入2.26亿+10 超大单主导+4; [融资4分] [盘中]融资买入占比100.0%+2 [盘中]融资主力同向+2; [锁仓3分] 流入加速+3",
      "sentiment": "[无] 竞价关注度较高(量比0.7)+1; 竞价成交619万+2",
      "shortterm": "[封板] 无涨停记录 | [连板] 近期无涨停 | [开盘] 今日无数据(最近20260522) | [板块] 无概念涨停统计 | [攻击] 无数据"
    },
    "weights": {
      "fundamental": "1.5",
      "technical": "1.0",
      "fundflow": "1.0",
      "sentiment": "1.2",
      "shortterm": "1.5"
    },
    "total": 55.42857142857143,
    "resonance": {
      "count": 1,
      "threshold": 75,
      "is_resonance": false
    },
    "top3_score": 55.4
  },
  {
    "code": "002845.SZ",
    "name": "同兴达",
    "scores": {
      "fundamental": 50.0,
      "technical": 45,
      "fundflow": 34,
      "sentiment": 5,
      "shortterm": 13.5
    },
    "reasons": {
      "fundamental": "[低] ROE=1.6%偏低; 扣非净利-7%; 10个概念; 近期5条公告; 解禁冲击低+0.1",
      "technical": "[低] 量能偏强(量比3.47)+10; 换手8.2%健康+5; 多头排列+15; 回踩MA10企稳+5; 下影支撑+4; 假突破:3日2日上影-4",
      "fundflow": "[无] [主力25分] 主力净流入[实时]14.1%+25; [龙虎9分] [盘中]封单22045.7%流通市值+10 [盘中]尾板140833-8 [盘中]秒封/一字板+7; [盘口0分] 净流出0.00亿; [融资0分] [盘中]无融资数据",
      "sentiment": "[无] 换手8.2%+1; 20日涨停+1; 竞价跳空1.7%[震荡态×1.0]→1分; 竞价关注度较高(量比0.5)+1; 竞价成交178万+1",
      "shortterm": "[封板] 今日未涨停(参考历史) | [连板] 断板(历史1连板); 近5日温和(均涨1.5%)+5 | [开盘] 今日无数据(最近20260522) | [板块] 无概念涨停统计 | [攻击] 近10日最大涨幅10.0%+35"
    },
    "weights": {
      "fundamental": "1.5",
      "technical": "1.0",
      "fundflow": "1.0",
      "sentiment": "1.2",
      "shortterm": "1.5"
    },
    "total": 44.0,
    "resonance": {
      "count": 0,
      "threshold": 75,
      "is_resonance": false
    },
    "top3_score": 44.0
  },
  {
    "code": "603890.SH",
    "name": "春秋电子",
    "scores": {
      "fundamental": 63.0,
      "technical": 40,
      "fundflow": 2,
      "sentiment": 17,
      "shortterm": 19.8
    },
    "reasons": {
      "fundamental": "[中] ROE=1.8%偏低; 扣非净利+83%; 8个概念; 解禁冲击低+0.1",
      "technical": "[低] 换手11.1%健康+5; 多头排列+15; 回踩MA10企稳+5; 波动收敛(带宽20.5%)+5; 价>中轨+2; 分时强势(回撤0.0%)+3",
      "fundflow": "[无] [主力0分] 主力净流入[T-1]0.00%-15; [龙虎0分] [盘中]封单5092.9%流通市值+10 [盘中]尾板94755-8 [盘中]开板5次-7; [盘口0分] 净流出1.05亿 对倒嫌疑换手11.1%-12; [融资2分] [盘中]融资买入占比100.0%+2",
      "sentiment": "[无] 换手11.1%+1; 20日涨停2次+3; 竞价跳空4.5%[震荡态×1.0]→3分; 竞价关注度极高(量比5.2)+5; 竞价量比6.1+3",
      "shortterm": "[封板] 今日未涨停(参考历史) | [连板] 断板(历史1连板); 近月4次涨停+10; 断板反包+15; 近5日温和(均涨2.8%)+5 | [开盘] 今日无数据(最近20260522) | [板块] 无概念涨停统计 | [攻击] 近10日最大涨幅10.0%+35"
    },
    "weights": {
      "fundamental": "1.5",
      "technical": "1.0",
      "fundflow": "1.0",
      "sentiment": "1.2",
      "shortterm": "1.5"
    },
    "total": 41.05,
    "resonance": {
      "count": 0,
      "threshold": 75,
      "is_resonance": false
    },
    "top3_score": 41.0
  },
  {
    "code": "601991.SH",
    "name": "大唐发电",
    "scores": {
      "fundamental": 62.0,
      "technical": 27,
      "fundflow": 2,
      "sentiment": 10,
      "shortterm": 29.0
    },
    "reasons": {
      "fundamental": "[中] 扣非净利+30%; 14个概念; 近期2条公告; 股东户数+53.8%; 解禁冲击低+0.1",
      "technical": "[无] 换手6.4%健康+5; 多头排列+15; 下影支撑+4; 假突破:3日3日上影-4; 价>中轨+2; 板块共振(45%>MA20)+5",
      "fundflow": "[无] [尾盘走弱]净流出3万+低于均价-5; [尾盘走弱]收跌+净流出+低于均价-5; [主力0分] 主力净流入[T-1]0.00%-15; [龙虎0分] [盘中]封单12543.7%流通市值+10 [盘中]T-1未涨停-15; [盘口0分] 净流出2.69亿; [融资2分] [盘中]融资买入占比100.0%+2",
      "sentiment": "[无] 换手6.4%+1; 20日涨停7次+3; 连板基因6连板+3; 竞价跳空-1.3%[震荡态×1.0]→0分; 竞价关注度较高(量比1.3)+1; 竞价成交7246万+2",
      "shortterm": "[封板] 今日未涨停(参考历史) | [连板] 断板(历史1连板); 近月7次涨停+20; 断板反包+15 | [开盘] 今日无数据(最近20260522) | [板块] 无概念涨停统计 | [攻击] 涨停高开率6/7>50%+40; 近10日最大涨幅10.0%+35"
    },
    "weights": {
      "fundamental": "1.5",
      "technical": "1.0",
      "fundflow": "1.0",
      "sentiment": "1.2",
      "shortterm": "1.5"
    },
    "total": 40.875,
    "resonance": {
      "count": 0,
      "threshold": 75,
      "is_resonance": false
    },
    "top3_score": 40.9
  },
  {
    "code": "000697.SZ",
    "name": "炼石航空",
    "scores": {
      "fundamental": 73.0,
      "technical": 16,
      "fundflow": 13,
      "sentiment": 3,
      "shortterm": 5.2
    },
    "reasons": {
      "fundamental": "[中] ROE=0.0%偏低; 扣非净利+96%; 营收+34%; 5个概念; 近期12条公告",
      "technical": "[无] 换手2.7%健康+5; 回踩MA20企稳+3; 下影支撑+4; 价>中轨+2; 板块中性(20%>MA20)+2",
      "fundflow": "[无] [主力0分] 主力净流入[T-1]-0.00%-15; [龙虎2分] [盘中]封单4573.9%流通市值+10 [盘中]尾板93500-8; [盘口4分] 超大单主导+4; [融资7分] [盘中]融资5日连增+3 [盘中]融资买入占比100.0%+2 [盘中]融资主力同向+2",
      "sentiment": "[无] 20日涨停+1; 竞价关注度较高(量比0.6)+1; 竞价成交124万+1",
      "shortterm": "[封板] 今日未涨停(参考历史) | [连板] 断板(历史1连板) | [开盘] 今日无数据(最近20260522) | [板块] 无概念涨停统计 | [攻击] 无数据"
    },
    "weights": {
      "fundamental": "1.5",
      "technical": "1.0",
      "fundflow": "1.0",
      "sentiment": "1.2",
      "shortterm": "1.5"
    },
    "total": 39.57142857142857,
    "resonance": {
      "count": 0,
      "threshold": 75,
      "is_resonance": false
    },
    "top3_score": 39.6
  },
  {
    "code": "000767.SZ",
    "name": "晋控电力",
    "scores": {
      "fundamental": 57.0,
      "technical": 34,
      "fundflow": 2,
      "sentiment": 13,
      "shortterm": 22.8
    },
    "reasons": {
      "fundamental": "[中] ROE=1.8%偏低; 13个概念; 近期5条公告; 股东户数-8.1%; 解禁冲击低+0.1",
      "technical": "[无] 换手12.5%健康+5; 多头排列+15; 回踩MA20企稳+3; 下影支撑+4; 价>中轨+2; 板块共振(45%>MA20)+5",
      "fundflow": "[无] [主力0分] 主力净流入[T-1]0.00%-15; [龙虎0分] [盘中]T-1未涨停-15; [盘口0分] 净流出2.53亿 对倒嫌疑换手12.5%-12; [融资2分] [盘中]融资买入占比100.0%+2",
      "sentiment": "[无] 换手12.5%+1; 20日涨停2次+3; 连板基因2连板+3; 竞价跳空1.5%[震荡态×1.0]→1分; 竞价关注度高(量比2.7)+3; 竞价成交4640万+2",
      "shortterm": "[封板] 今日未涨停(参考历史) | [连板] 断板(历史2连板); 近月4次涨停+10 | [开盘] 今日无数据(最近20260522) | [板块] 无概念涨停统计 | [攻击] 涨停高开率2/2>50%+40; 近10日最大涨幅10.1%+35"
    },
    "weights": {
      "fundamental": "1.5",
      "technical": "1.0",
      "fundflow": "1.0",
      "sentiment": "1.2",
      "shortterm": "1.5"
    },
    "total": 38.425,
    "resonance": {
      "count": 0,
      "threshold": 75,
      "is_resonance": false
    },
    "top3_score": 38.4
  },
  {
    "code": "603688.SH",
    "name": "石英股份",
    "scores": {
      "fundamental": 46.0,
      "technical": 24,
      "fundflow": 20,
      "sentiment": 0,
      "shortterm": 24.0
    },
    "reasons": {
      "fundamental": "[低] ROE=2.6%偏低; 扣非净利-3%; 6个概念; 近期2条公告; 解禁冲击低+0.1",
      "technical": "[无] 换手7.2%健康+5; 回踩MA10企稳+5; 下影支撑+4; 价>中轨+2; 分时强势(回撤1.2%)+3; 板块共振(60%>MA20)+5",
      "fundflow": "[无] [主力0分] 主力净流入[T-1]-0.00%-15; [龙虎13分] [盘中]封单2953.9%流通市值+10 [盘中]开板1次+3; [融资4分] [盘中]融资买入占比100.0%+2 [盘中]融资主力同向+2; [锁仓3分] 流入加速+3",
      "sentiment": "纯跟风弱势:涨幅仅0.0%<3%",
      "shortterm": "[封板] 今日未涨停(参考历史) | [连板] 断板(历史1连板); 断板反包+15; 近5日温和(均涨1.4%)+5 | [开盘] 今日无数据(最近20260522); 实时换手偏大(7455.0%)+15; 实时量比127.0+10 | [板块] 无概念涨停统计 | [攻击] 近10日最大涨幅10.0%+35 | [竞价] 竞价正常(量比127.0开-97.4%)+5; 竞价换手7455.00%+5"
    },
    "weights": {
      "fundamental": "1.5",
      "technical": "1.0",
      "fundflow": "1.0",
      "sentiment": "1.2",
      "shortterm": "1.5"
    },
    "total": 32.25,
    "resonance": {
      "count": 0,
      "threshold": 75,
      "is_resonance": false
    },
    "top3_score": 32.2
  },
  {
    "code": "603773.SH",
    "name": "沃格光电",
    "scores": {
      "fundamental": 0,
      "technical": 35,
      "fundflow": 25,
      "sentiment": 8,
      "shortterm": 30.2
    },
    "reasons": {
      "fundamental": "财务避雷否决: 扣非净利润连续亏损(无困境反转)",
      "technical": "[低] 量能偏强(量比1.88)+10; 换手13.5%健康+5; 回踩MA10企稳+5; 下影支撑+4; 假突破:3日2日上影-4; 波动收敛(带宽45.1%)+5",
      "fundflow": "[无] [尾盘走弱]净流出2万+低于均价-5; [尾盘走弱]收跌+净流出+低于均价-5; [主力25分] 主力净流入[实时]3.2%+25; [龙虎0分] [盘中]T-1未涨停-15; [盘口0分] 净流出2.03亿 对倒嫌疑换手13.5%-12; [融资0分] [盘中]无融资数据",
      "sentiment": "[无] 换手13.5%+1; 20日涨停+1; 连板基因2连板+3; 竞价关注度较高(量比1.1)+1; 竞价成交2732万+2",
      "shortterm": "[封板] 今日未涨停(参考历史) | [连板] 断板(历史1连板); 近月9次涨停+20; 断板反包+15; 近5日温和(均涨1.5%)+5 | [开盘] 今日无数据(最近20260522) | [板块] 无概念涨停统计 | [攻击] 涨停高开率4/5>50%+40; 近10日最大涨幅10.0%+35"
    },
    "weights": {
      "fundamental": "1.5",
      "technical": "1.0",
      "fundflow": "1.0",
      "sentiment": "1.2",
      "shortterm": "1.5"
    },
    "total": 30.085714285714285,
    "resonance": {
      "count": 0,
      "threshold": 75,
      "is_resonance": false
    },
    "top3_score": 30.1
  },
  {
    "code": "600459.SH",
    "name": "贵研铂业",
    "scores": {
      "fundamental": 60.0,
      "technical": 0,
      "fundflow": 12,
      "sentiment": 3,
      "shortterm": 8.5
    },
    "reasons": {
      "fundamental": "[中] 20个概念; 近期5条公告; 解禁冲击低+0.1; 负债率65%",
      "technical": "资金持续出逃:近2日净流出+收盘/中轨0.961<0.99",
      "fundflow": "[无] [主力0分] 主力净流入[T-1]-0.00%-15 散户接盘[T-1]-20; [龙虎0分] [盘中]T-1未涨停-15; [盘口10分] 持续净流入0.36亿+10 超大单主导+4; [融资2分] [盘中]融资买入占比100.0%+2",
      "sentiment": "[无] 竞价跳空1.8%[震荡态×1.0]→1分; 竞价关注度较高(量比0.9)+1; 竞价成交295万+1",
      "shortterm": "[封板] 无涨停记录 | [连板] 近期无涨停 | [开盘] 今日无数据(最近20260522) | [板块] 无概念涨停统计 | [攻击] 近10日最大涨幅7.6%+35"
    },
    "weights": {
      "fundamental": "1.5",
      "technical": "1.0",
      "fundflow": "1.0",
      "sentiment": "1.2",
      "shortterm": "1.5"
    },
    "total": 28.6875,
    "resonance": {
      "count": 0,
      "threshold": 75,
      "is_resonance": false
    },
    "top3_score": 28.7
  },
  {
    "code": "600396.SH",
    "name": "华电辽能",
    "scores": {
      "fundamental": 44.0,
      "technical": 16,
      "fundflow": 10,
      "sentiment": 11,
      "shortterm": 21.0
    },
    "reasons": {
      "fundamental": "[低] ROE=2.1%偏低; 5个概念; 股东户数+227.6%; 解禁冲击低+0.1; 负债率69%",
      "technical": "[无] 换手13.1%健康+5; 下影支撑+4; 价>中轨+2; 板块共振(45%>MA20)+5",
      "fundflow": "[无] [主力0分] 主力净流入[T-1]-0.00%-15; [龙虎0分] [盘中]封单7423.1%流通市值+10 [盘中]T-1未涨停-15; [盘口10分] 强承接换手/振幅2.3+6 超大单主导+4; [融资0分] [盘中]无融资数据",
      "sentiment": "[无] 换手13.1%+1; 20日涨停5次+3; 连板基因8连板+3; 竞价跳空1.3%[震荡态×1.0]→1分; 竞价关注度较高(量比1.4)+1; 竞价成交4067万+2",
      "shortterm": "[封板] 今日未涨停(参考历史) | [连板] 断板(历史3连板); 近月11次涨停+20; 断板反包+15 | [开盘] 今日无数据(最近20260522) | [板块] 无概念涨停统计 | [攻击] 近10日最大涨幅10.0%+35"
    },
    "weights": {
      "fundamental": "1.5",
      "technical": "1.0",
      "fundflow": "1.0",
      "sentiment": "1.2",
      "shortterm": "1.5"
    },
    "total": 28.375,
    "resonance": {
      "count": 0,
      "threshold": 75,
      "is_resonance": false
    },
    "top3_score": 28.4
  },
  {
    "code": "603976.SH",
    "name": "正川股份",
    "scores": {
      "fundamental": 0,
      "technical": 32,
      "fundflow": 37,
      "sentiment": 17,
      "shortterm": 20.2
    },
    "reasons": {
      "fundamental": "评分异常: name 'safe_safe_float' is not defined",
      "technical": "[无] 换手6.2%健康+5; 多头排列+15; 回踩MA10企稳+5; 价>中轨+2; 分时强势(回撤0.0%)+3; 板块中性(35%>MA20)+2",
      "fundflow": "[低] [主力0分] 主力净流入[T-1]0.00%-15; [龙虎17分] [盘中]封单12060.6%流通市值+10 [盘中]秒封/一字板+7; [盘口10分] 持续净流入0.08亿+10 超大单主导+4; [融资0分] [盘中]无融资数据; [锁仓10分] 流入递增锁仓+7 流入加速+3",
      "sentiment": "[无] 换手6.2%+1; 20日涨停+1; 竞价跳空7.4%[震荡态×1.0]→5分; 竞价关注度极高(量比4.3)+5; 竞价量比9.6+3",
      "shortterm": "[封板] 今日未涨停(参考历史) | [连板] 断板(历史1连板); 近5日温和(均涨2.5%)+5 | [开盘] 今日无数据(最近20260522); 实时换手偏大(2420.0%)+15; 实时量比2527.0+10 | [板块] 无概念涨停统计 | [攻击] 近10日最大涨幅10.0%+35 | [竞价] 竞价正常(量比2527.0开-93.4%)+5; 竞价换手2420.00%+5"
    },
    "weights": {
      "fundamental": "1.5",
      "technical": "1.0",
      "fundflow": "1.0",
      "sentiment": "1.2",
      "shortterm": "1.5"
    },
    "total": 28.37142857142857,
    "resonance": {
      "count": 0,
      "threshold": 75,
      "is_resonance": false
    },
    "top3_score": 28.4
  },
  {
    "code": "600719.SH",
    "name": "大连热电",
    "scores": {
      "fundamental": 0,
      "technical": 15,
      "fundflow": 34,
      "sentiment": 17,
      "shortterm": 29.0
    },
    "reasons": {
      "fundamental": "财务避雷否决: 负债率82%>70%且经营现金流为负",
      "technical": "[无] 换手10.5%健康+5; 回踩MA20企稳+3; 价>中轨+2; 分时强势(回撤0.2%)+3; 板块中性(35%>MA20)+2",
      "fundflow": "[无] [主力0分] 主力净流入[T-1]0.00%-15; [龙虎17分] [盘中]封单19525.5%流通市值+10 [盘中]秒封/一字板+7; [盘口10分] 持续净流入0.16亿+10 超大单主导+4; [融资0分] [盘中]无融资数据; [锁仓7分] 流入递增锁仓+7",
      "sentiment": "[无] 换手10.5%+1; 20日涨停4次+3; 连板基因2连板+3; 竞价跳空3.2%[震荡态×1.0]→3分; 竞价关注度极高(量比3.0)+5; 竞价成交1189万+2",
      "shortterm": "[封板] 今日未涨停(参考历史) | [连板] 断板(历史1连板); 近月5次涨停+20; 断板反包+15 | [开盘] 今日无数据(最近20260522) | [板块] 无概念涨停统计 | [攻击] 涨停高开率3/4>50%+40; 近10日最大涨幅10.1%+35"
    },
    "weights": {
      "fundamental": "1.5",
      "technical": "1.0",
      "fundflow": "1.0",
      "sentiment": "1.2",
      "shortterm": "1.5"
    },
    "total": 26.45945945945946,
    "resonance": {
      "count": 0,
      "threshold": 75,
      "is_resonance": false
    },
    "top3_score": 26.5
  },
  {
    "code": "002534.SZ",
    "name": "西子洁能",
    "scores": {
      "fundamental": 44.0,
      "technical": 12,
      "fundflow": 11,
      "sentiment": 3,
      "shortterm": 9.8
    },
    "reasons": {
      "fundamental": "[低] ROE=1.1%偏低; 扣非净利-26%; 8个概念; 近期2条公告; 解禁冲击低+0.1",
      "technical": "[无] 换手1.4%健康+5; MA60下倾-5; 回踩MA10企稳+5; 下影支撑+4; 假突破:3日2日上影-4; 价>中轨+2",
      "fundflow": "[无] [尾盘走弱]净流出0万+低于均价-5; [主力0分] 主力净流入[T-1]0.00%-15; [龙虎9分] [盘中]封单10027.1%流通市值+10 [盘中]尾板94730-8 [盘中]秒封/一字板+7; [盘口0分] 净流出0.07亿; [融资2分] [盘中]融资买入占比100.0%+2",
      "sentiment": "[无] 竞价跳空2.1%[震荡态×1.0]→1分; 竞价关注度较高(量比0.7)+1; 竞价成交147万+1",
      "shortterm": "[封板] 无涨停记录 | [连板] 近期无涨停; 近5日温和(均涨1.7%)+5 | [开盘] 今日无数据(最近20260522) | [板块] 无概念涨停统计 | [攻击] 近10日最大涨幅7.8%+35"
    },
    "weights": {
      "fundamental": "1.5",
      "technical": "1.0",
      "fundflow": "1.0",
      "sentiment": "1.2",
      "shortterm": "1.5"
    },
    "total": 23.175,
    "resonance": {
      "count": 0,
      "threshold": 75,
      "is_resonance": false
    },
    "top3_score": 23.2
  },
  {
    "code": "605500.SH",
    "name": "森林包装",
    "scores": {
      "fundamental": 0,
      "technical": 31,
      "fundflow": 13,
      "sentiment": 12,
      "shortterm": 20.2
    },
    "reasons": {
      "fundamental": "财务避雷否决: 扣非净利润连续亏损(无困境反转)",
      "technical": "[无] 换手8.1%健康+5; 多头排列+15; 回踩MA10企稳+5; 下影支撑+4; 价>中轨+2; 板块弱势(<20%>MA20)天花板74分",
      "fundflow": "[无] [主力0分] 主力净流入[T-1]0.00%-15; [龙虎13分] [盘中]封单6867.9%流通市值+10 [盘中]开板1次+3; [盘口0分] 净流出0.73亿; [融资0分] [盘中]无融资数据",
      "sentiment": "[无] 换手8.1%+1; 20日涨停+1; 竞价跳空-6.4%[震荡态×1.0]→0分; 竞价关注度极高(量比10.7)+5; 竞价量比26.0+3",
      "shortterm": "[封板] 今日未涨停(参考历史) | [连板] 断板(历史1连板); 近5日温和(均涨3.0%)+5 | [开盘] 今日无数据(最近20260522); 实时换手偏大(1088.0%)+15; 实时量比1391.0+10 | [板块] 无概念涨停统计 | [攻击] 近10日最大涨幅10.0%+35 | [竞价] 竞价正常(量比1391.0开-99.7%)+5; 竞价换手1088.00%+5"
    },
    "weights": {
      "fundamental": "1.5",
      "technical": "1.0",
      "fundflow": "1.0",
      "sentiment": "1.2",
      "shortterm": "1.5"
    },
    "total": 20.459459459459456,
    "resonance": {
      "count": 0,
      "threshold": 75,
      "is_resonance": false
    },
    "top3_score": 20.5
  },
  {
    "code": "600707.SH",
    "name": "彩虹股份",
    "scores": {
      "fundamental": 0,
      "technical": 27,
      "fundflow": 0,
      "sentiment": 10,
      "shortterm": 21.0
    },
    "reasons": {
      "fundamental": "财务避雷否决: 扣非净利润连续亏损(无困境反转)",
      "technical": "[无] 换手7.5%健康+5; 暴量滞涨(换手7.5%)-10; 多头排列+15; 回踩MA10企稳+5; 下影支撑+4; 假突破:3日2日上影-4",
      "fundflow": "[无] [主力0分] 主力净流入[T-1]-0.00%-15 散户接盘[T-1]-20; [龙虎0分] [盘中]T-1未涨停-15; [融资0分] [盘中]融资买入占比100.0%+2 [盘中]融资3日连降-5",
      "sentiment": "[无] 换手7.5%+1; 20日涨停2次+3; 连板基因2连板+3; 竞价关注度较高(量比1.1)+1; 竞价成交3214万+2",
      "shortterm": "[封板] 今日未涨停(参考历史) | [连板] 断板(历史1连板); 近月7次涨停+20; 断板反包+15 | [开盘] 今日无数据(最近20260522) | [板块] 无概念涨停统计 | [攻击] 近10日最大涨幅10.0%+35"
    },
    "weights": {
      "fundamental": "1.5",
      "technical": "1.0",
      "fundflow": "1.0",
      "sentiment": "1.2",
      "shortterm": "1.5"
    },
    "total": 19.054054054054053,
    "resonance": {
      "count": 0,
      "threshold": 75,
      "is_resonance": false
    },
    "top3_score": 19.1
  },
  {
    "code": "600821.SH",
    "name": "金开新能",
    "scores": {
      "fundamental": 0,
      "technical": 0,
      "fundflow": 30,
      "sentiment": 0,
      "shortterm": 5.2
    },
    "reasons": {
      "fundamental": "财务避雷否决: 扣非净利润连续亏损(无困境反转)",
      "technical": "放量破位:收盘8.13<MA20=8.67,量比0.99>Top20%",
      "fundflow": "[无] [主力25分] 主力净流入[实时]3.7%+25; [龙虎3分] [盘中]封单2619.5%流通市值+10 [盘中]开板6次-7; [盘口0分] 净流出0.86亿; [融资2分] [盘中]融资买入占比100.0%+2",
      "sentiment": "纯跟风弱势:涨幅仅0.0%<3%",
      "shortterm": "[封板] 今日未涨停(参考历史) | [连板] 断板(历史1连板) | [开盘] 今日无数据(最近20260522) | [板块] 无概念涨停统计 | [攻击] 无数据"
    },
    "weights": {
      "fundamental": "1.5",
      "technical": "1.0",
      "fundflow": "1.0",
      "sentiment": "1.2",
      "shortterm": "1.5"
    },
    "total": 9.45,
    "resonance": {
      "count": 0,
      "threshold": 75,
      "is_resonance": false
    },
    "top3_score": 9.4
  }
]